.gitignore
AUTHORS.rst
CONTRIBUTING.rst
HISTORY.rst
LICENSE
MANIFEST.in
README.rst
setup.cfg
setup.py
docs/Makefile
docs/authors.rst
docs/conf.py
docs/contributing.rst
docs/history.rst
docs/index.rst
docs/installation.rst
docs/make.bat
docs/readme.rst
docs/usage.rst
sentinel2/__init__.py
sentinel2/s6.py
sentinel2/sentinel2.py
sentinel2.egg-info/PKG-INFO
sentinel2.egg-info/SOURCES.txt
sentinel2.egg-info/dependency_links.txt
sentinel2.egg-info/not-zip-safe
sentinel2.egg-info/top_level.txt
tests/__init__.py
tests/test_sentinel2.py