Metadata-Version: 1.2
Name: sentinel2
Version: 0.0.1
Summary: A Python package for processing Sentinel-2 Level-1C product
Home-page: https://github.com/csaybar/sentinel2
Author: Cesar Aybar Camacho
Author-email: csaybar@gmail.com
License: GNU General Public License v3
Keywords: sentinel2
Platform: UNKNOWN
Classifier: Development Status :: 2 - Pre-Alpha
Classifier: Intended Audience :: Developers
Classifier: License :: OSI Approved :: GNU General Public License v3 (GPLv3)
Classifier: Natural Language :: English
Classifier: Programming Language :: Python :: 3
Classifier: Programming Language :: Python :: 3.5
Classifier: Programming Language :: Python :: 3.6
Classifier: Programming Language :: Python :: 3.7
Classifier: Programming Language :: Python :: 3.8
Requires-Python: >=3.5
